dsf_api_sdk/__init__.py
dsf_api_sdk/client.py
dsf_api_sdk/exceptions.py
dsf_api_sdk/models.py
dsf_api_sdk-1.0.3.dist-info/METADATA
dsf_api_sdk-1.0.3.dist-info/WHEEL
dsf_api_sdk-1.0.3.dist-info/top_level.txt
dsf_api_sdk-1.0.3.dist-info/RECORD
