Metadata-Version: 2.1
Name: dsf-api-sdk
Version: 1.0.3
Summary: SDK for DSF API Validation
Home-page: https://github.com/jaimeajl/dsf-api-sdk
Author: Jaime Alexander Jimenez
Author-email: contacto@softwarefinanzas.com.co
License: UNKNOWN
Keywords: dsf api validation request evaluation sdk
Platform: UNKNOWN
Classifier: Development Status :: 5 - Production/Stable
Classifier: Intended Audience :: Developers
Classifier: License :: OSI Approved :: MIT License
Classifier: Programming Language :: Python :: 3
Classifier: Programming Language :: Python :: 3.7
Classifier: Programming Language :: Python :: 3.8
Classifier: Programming Language :: Python :: 3.9
Classifier: Programming Language :: Python :: 3.10
Classifier: Programming Language :: Python :: 3.11
Requires-Python: >=3.7
Requires-Dist: requests>=2.25.0
